hackathon/__init__.py
hackathon/data/fetch.py
hackathon/data/product_reviews.xlsx
hackathon/env.py
hackathon/evaluation/country_inferring.py
hackathon/evaluation/country_ratings_analysis.py
hackathon/evaluation/solution_location_country_mapping.xlsx
hackathon/helpers.py
hackathon/paths.py
be_genai_workshop_short-0.1.2.0.dist-info/METADATA
be_genai_workshop_short-0.1.2.0.dist-info/WHEEL
be_genai_workshop_short-0.1.2.0.dist-info/RECORD
