Metadata-Version: 2.1
Name: be-genai-workshop-short
Version: 0.1.2.0
Summary: 
Requires-Python: >=3.10.12,<4.0.0
Classifier: Programming Language :: Python :: 3
Classifier: Programming Language :: Python :: 3.11
Classifier: Programming Language :: Python :: 3.12
Requires-Dist: ipykernel (==5.5.6)
Requires-Dist: ipython (>=7)
Requires-Dist: ipywidgets (>=7.7)
Requires-Dist: jupyter (>=1.1.1,<2.0.0)
Requires-Dist: matplotlib (>=3.7,<4.0)
Requires-Dist: numpy (>=1.26.4)
Requires-Dist: openai (>=1,<2)
Requires-Dist: openpyxl (>=3,<4)
Requires-Dist: pandas (>=2.1.4)
Requires-Dist: python-dotenv (>=1,<2)
Requires-Dist: seaborn (>=0.13,<0.14)
Requires-Dist: tqdm (>=4.66.5,<5.0.0)
